config_core/__init__.py
config_core/config_helper.py
config_core-0.0.1.dist-info/licenses/LICENSE.txt
config_core-0.0.1.dist-info/METADATA
config_core-0.0.1.dist-info/WHEEL
config_core-0.0.1.dist-info/top_level.txt
config_core-0.0.1.dist-info/RECORD
