Metadata-Version: 2.4
Name: config-core
Version: 0.0.1
Summary: Add a short description here!
Author: jarneamerlinck-do
License: Proprietary
Project-URL: Documentation, https://pyscaffold.org/
Platform: any
Classifier: Development Status :: 4 - Beta
Classifier: Programming Language :: Python
License-File: LICENSE.txt
Requires-Dist: importlib-metadata; python_version < "3.9"
Requires-Dist: pydantic>=2.12.0
Requires-Dist: python-dotenv<=1.0.1
Provides-Extra: testing
Requires-Dist: setuptools; extra == "testing"
Requires-Dist: pytest; extra == "testing"
Requires-Dist: pytest-cov; extra == "testing"
Requires-Dist: coverage; extra == "testing"
Requires-Dist: parameterized; extra == "testing"
Requires-Dist: pyyaml; extra == "testing"
Dynamic: license-file
